User/__init__.py
User/q2.py
user_account-0.1.dist-info/License.txt
user_account-0.1.dist-info/METADATA
user_account-0.1.dist-info/WHEEL
user_account-0.1.dist-info/top_level.txt
user_account-0.1.dist-info/RECORD
