Metadata-Version: 2.1
Name: user-account
Version: 0.1
Summary: OTT Platform
Author: Prathamesh72
Author-email: pspwork72@gmail.com
License: MIT
License-File: License.txt
